ai_lls_lib/__init__.py
ai_lls_lib/admin/__init__.py
ai_lls_lib/admin/service.py
ai_lls_lib/auth/__init__.py
ai_lls_lib/auth/context_parser.py
ai_lls_lib/cli/__init__.py
ai_lls_lib/cli/__main__.py
ai_lls_lib/cli/aws_client.py
ai_lls_lib/cli/commands/__init__.py
ai_lls_lib/cli/commands/admin.py
ai_lls_lib/cli/commands/cache.py
ai_lls_lib/cli/commands/monitor.py
ai_lls_lib/cli/commands/stripe.py
ai_lls_lib/cli/commands/test_stack.py
ai_lls_lib/cli/commands/verify.py
ai_lls_lib/cli/env_loader.py
ai_lls_lib/core/__init__.py
ai_lls_lib/core/cache.py
ai_lls_lib/core/models.py
ai_lls_lib/core/processor.py
ai_lls_lib/core/verifier.py
ai_lls_lib/payment/__init__.py
ai_lls_lib/payment/credit_manager.py
ai_lls_lib/payment/models.py
ai_lls_lib/payment/stripe_manager.py
ai_lls_lib/payment/webhook_processor.py
ai_lls_lib/providers/__init__.py
ai_lls_lib/providers/base.py
ai_lls_lib/providers/external.py
ai_lls_lib-3.1.0.dist-info/WHEEL
ai_lls_lib-3.1.0.dist-info/entry_points.txt
ai_lls_lib-3.1.0.dist-info/METADATA
ai_lls_lib-3.1.0.dist-info/RECORD
