Metadata-Version: 2.3
Name: ai-lls-lib
Version: 3.1.0
Summary: Landline Scrubber core library - phone verification and DNC checking
Author: LandlineScrubber Team
Requires-Dist: boto3>=1.34.0
Requires-Dist: pydantic>=2.5.0
Requires-Dist: phonenumbers>=8.13.0
Requires-Dist: httpx>=0.25.0
Requires-Dist: aws-lambda-powertools>=2.30.0
Requires-Dist: click>=8.1.0
Requires-Dist: rich>=14.0
Requires-Dist: stripe>=12.5.1
Requires-Dist: pytest>=7.4.0 ; extra == 'dev'
Requires-Dist: pytest-cov>=4.1.0 ; extra == 'dev'
Requires-Dist: pytest-asyncio>=0.21.0 ; extra == 'dev'
Requires-Dist: ruff>=0.8.0 ; extra == 'dev'
Requires-Dist: mypy>=1.8.0 ; extra == 'dev'
Requires-Dist: boto3-stubs[dynamodb,s3,sqs]>=1.34.0 ; extra == 'dev'
Requires-Dist: moto[dynamodb,s3,sqs]>=4.2.0 ; extra == 'dev'
Requires-Dist: python-semantic-release>=10.3.1 ; extra == 'dev'
Requires-Dist: pre-commit>=4.0.0 ; extra == 'dev'
Requires-Dist: bandit>=1.7.0 ; extra == 'dev'
Requires-Dist: safety>=3.0.0 ; extra == 'dev'
Requires-Dist: pip-audit>=2.7.0 ; extra == 'dev'
Requires-Dist: pip-licenses>=5.0.0 ; extra == 'dev'
Requires-Dist: pdoc>=15.0.0 ; extra == 'dev'
Requires-Dist: pytest-html>=4.0.0 ; extra == 'dev'
Requires-Python: >=3.12
Provides-Extra: dev
